pytest_jubilant/__init__.py
pytest_jubilant/main.py
pytest_jubilant/version.py
pytest_jubilant-1.1.dist-info/licenses/LICENSE
pytest_jubilant-1.1.dist-info/METADATA
pytest_jubilant-1.1.dist-info/WHEEL
pytest_jubilant-1.1.dist-info/entry_points.txt
pytest_jubilant-1.1.dist-info/top_level.txt
pytest_jubilant-1.1.dist-info/RECORD
