Metadata-Version: 2.4
Name: pytest-jubilant
Version: 1.1
Summary: Add your description here
License-Expression: Apache-2.0
Project-URL: Homepage, https://github.com/canonical/pytest-jubilant
Project-URL: Issues, https://github.com/canonical/pytest-jubilant/issues
Classifier: Programming Language :: Python :: 3
Classifier: Operating System :: OS Independent
Requires-Python: >=3.8
License-File: LICENSE
Requires-Dist: jubilant>=0.5.0
Requires-Dist: pytest>=8.3.5
Dynamic: license-file
